README.md
setup.py
perf_serve/__init__.py
perf_serve/__main__.py
perf_serve/args.py
perf_serve/interfaces.py
perf_serve/main.py
perf_serve/perf_script.py
perf_serve/server.py
perf_serve.egg-info/PKG-INFO
perf_serve.egg-info/SOURCES.txt
perf_serve.egg-info/dependency_links.txt
perf_serve.egg-info/not-zip-safe
perf_serve.egg-info/requires.txt
perf_serve.egg-info/top_level.txt