Metadata-Version: 1.0
Name: perf-serve
Version: 0.1
Summary: Easily serve linux perf profile for firefox profiler
Home-page: https://github.com/forestryks/perf-serve
Author: Andrei Odintsov
Author-email: forestryks1@gmail.com
License: MIT
Platform: UNKNOWN
